{
    "1": {
        "name": "New Jersey Devils",
        "code": "NJD"
    },
    "2": {
        "name": "New York Islanders",
        "code": "NYI"
    },
    "3": {
        "name": "New York Rangers",
        "code": "NYR"
    },
    "4": {
        "name": "Philadelphia Flyers",
        "code": "PHI"
    },
    "5": {
        "name": "Pittsburgh Penguins",
        "code": "PIT"
    },
    "6": {
        "name": "Boston Bruins",
        "code": "BOS"
    },
    "7": {
        "name": "Buffalo Sabres",
        "code": "BUF"
    },
    "8": {
        "name": "Montr\u00e9al Canadiens",
        "code": "MTL"
    },
    "9": {
        "name": "Ottawa Senators",
        "code": "OTT"
    },
    "10": {
        "name": "Toronto Maple Leafs",
        "code": "TOR"
    },
    "12": {
        "name": "Carolina Hurricanes",
        "code": "CAR"
    },
    "13": {
        "name": "Florida Panthers",
        "code": "FLA"
    },
    "14": {
        "name": "Tampa Bay Lightning",
        "code": "TBL"
    },
    "15": {
        "name": "Washington Capitals",
        "code": "WSH"
    },
    "16": {
        "name": "Chicago Blackhawks",
        "code": "CHI"
    },
    "17": {
        "name": "Detroit Red Wings",
        "code": "DET"
    },
    "18": {
        "name": "Nashville Predators",
        "code": "NSH"
    },
    "19": {
        "name": "St. Louis Blues",
        "code": "STL"
    },
    "20": {
        "name": "Calgary Flames",
        "code": "CGY"
    },
    "21": {
        "name": "Colorado Avalanche",
        "code": "COL"
    },
    "22": {
        "name": "Edmonton Oilers",
        "code": "EDM"
    },
    "23": {
        "name": "Vancouver Canucks",
        "code": "VAN"
    },
    "24": {
        "name": "Anaheim Ducks",
        "code": "ANA"
    },
    "25": {
        "name": "Dallas Stars",
        "code": "DAL"
    },
    "26": {
        "name": "Los Angeles Kings",
        "code": "LAK"
    },
    "28": {
        "name": "San Jose Sharks",
        "code": "SJS"
    },
    "29": {
        "name": "Columbus Blue Jackets",
        "code": "CBJ"
    },
    "30": {
        "name": "Minnesota Wild",
        "code": "MIN"
    },
    "52": {
        "name": "Winnipeg Jets",
        "code": "WPG"
    },
    "53": {
        "name": "Arizona Coyotes",
        "code": "ARI"
    },
    "54": {
        "name": "Vegas Golden Knights",
        "code": "VGK"
    },
    "55": {
        "name": "Seattle Kraken",
        "code": "SEA"
    }
}